{
  "errorTips": "We use Git LFS to manage large files in our Monorepo",
  "checkPattern": {
    "**/*.3dm": -1,
    "**/*.3ds": -1,
    "**/*.3g2": -1,
    "**/*.3gp": -1,
    "**/*.7z": -1,
    "**/*.a": -1,
    "**/*.aac": -1,
    "**/*.adp": -1,
    "**/*.ai": -1,
    "**/*.aif": -1,
    "**/*.aiff": -1,
    "**/*.alz": -1,
    "**/*.ape": -1,
    "**/*.apk": -1,
    "**/*.appimage": -1,
    "**/*.ar": -1,
    "**/*.arj": -1,
    "**/*.asf": -1,
    "**/*.au": -1,
    "**/*.avi": -1,
    "**/*.bak": -1,
    "**/*.baml": -1,
    "**/*.bh": -1,
    "**/*.bin": -1,
    "**/*.bk": -1,
    "**/*.bmp": -1,
    "**/*.btif": -1,
    "**/*.bz2": -1,
    "**/*.bzip2": -1,
    "**/*.cab": -1,
    "**/*.caf": -1,
    "**/*.cgm": -1,
    "**/*.class": -1,
    "**/*.cmx": -1,
    "**/*.cpio": -1,
    "**/*.cr2": -1,
    "**/*.cur": -1,
    "**/*.dat": -1,
    "**/*.dcm": -1,
    "**/*.deb": -1,
    "**/*.dex": -1,
    "**/*.djvu": -1,
    "**/*.dll": -1,
    "**/*.dmg": -1,
    "**/*.dng": -1,
    "**/*.doc": -1,
    "**/*.docm": -1,
    "**/*.docx": -1,
    "**/*.dot": -1,
    "**/*.dotm": -1,
    "**/*.dra": -1,
    "**/*.DS_Store": -1,
    "**/*.dsk": -1,
    "**/*.dts": -1,
    "**/*.dtshd": -1,
    "**/*.dvb": -1,
    "**/*.dwg": -1,
    "**/*.dxf": -1,
    "**/*.ecelp4800": -1,
    "**/*.ecelp7470": -1,
    "**/*.ecelp9600": -1,
    "**/*.egg": -1,
    "**/*.eol": -1,
    "**/*.eot": -1,
    "**/*.epub": -1,
    "**/*.exe": -1,
    "**/*.f4v": -1,
    "**/*.fbs": -1,
    "**/*.fh": -1,
    "**/*.fla": -1,
    "**/*.flac": -1,
    "**/*.flatpak": -1,
    "**/*.fli": -1,
    "**/*.flv": -1,
    "**/*.fpx": -1,
    "**/*.fst": -1,
    "**/*.fvt": -1,
    "**/*.g3": -1,
    "**/*.gh": -1,
    "**/*.gif": -1,
    "**/*.graffle": -1,
    "**/*.gz": -1,
    "**/*.gzip": -1,
    "**/*.h261": -1,
    "**/*.h263": -1,
    "**/*.h264": -1,
    "**/*.icns": -1,
    "**/*.ico": -1,
    "**/*.ief": -1,
    "**/*.img": -1,
    "**/*.ipa": -1,
    "**/*.iso": -1,
    "**/*.jar": -1,
    "**/*.jpeg": -1,
    "**/*.jpg": -1,
    "**/*.jpgv": -1,
    "**/*.jpm": -1,
    "**/*.jxr": -1,
    "**/*.key": -1,
    "**/*.ktx": -1,
    "**/*.lha": -1,
    "**/*.lib": -1,
    "**/*.lvp": -1,
    "**/*.lz": -1,
    "**/*.lzh": -1,
    "**/*.lzma": -1,
    "**/*.lzo": -1,
    "**/*.m3u": -1,
    "**/*.m4a": -1,
    "**/*.m4v": -1,
    "**/*.mar": -1,
    "**/*.mdi": -1,
    "**/*.mht": -1,
    "**/*.mid": -1,
    "**/*.midi": -1,
    "**/*.mj2": -1,
    "**/*.mka": -1,
    "**/*.mkv": -1,
    "**/*.mmr": -1,
    "**/*.mng": -1,
    "**/*.mobi": -1,
    "**/*.mov": -1,
    "**/*.movie": -1,
    "**/*.mp3": -1,
    "**/*.mp4": -1,
    "**/*.mp4a": -1,
    "**/*.mpeg": -1,
    "**/*.mpg": -1,
    "**/*.mpga": -1,
    "**/*.mxu": -1,
    "**/*.nef": -1,
    "**/*.npx": -1,
    "**/*.numbers": -1,
    "**/*.nupkg": -1,
    "**/*.o": -1,
    "**/*.odp": -1,
    "**/*.ods": -1,
    "**/*.odt": -1,
    "**/*.oga": -1,
    "**/*.ogg": -1,
    "**/*.ogv": -1,
    "**/*.otf": -1,
    "**/*.ott": -1,
    "**/*.pages": -1,
    "**/*.pbm": -1,
    "**/*.pcx": -1,
    "**/*.pdb": -1,
    "**/*.pdf": -1,
    "**/*.pea": -1,
    "**/*.pgm": -1,
    "**/*.pic": -1,
    "**/*.png": -1,
    "**/*.pnm": -1,
    "**/*.pot": -1,
    "**/*.potm": -1,
    "**/*.potx": -1,
    "**/*.ppa": -1,
    "**/*.ppam": -1,
    "**/*.ppm": -1,
    "**/*.pps": -1,
    "**/*.ppsm": -1,
    "**/*.ppsx": -1,
    "**/*.ppt": -1,
    "**/*.pptm": -1,
    "**/*.pptx": -1,
    "**/*.psd": -1,
    "**/*.pya": -1,
    "**/*.pyc": -1,
    "**/*.pyo": -1,
    "**/*.pyv": -1,
    "**/*.qt": -1,
    "**/*.rar": -1,
    "**/*.ras": -1,
    "**/*.raw": -1,
    "**/*.resources": -1,
    "**/*.rgb": -1,
    "**/*.rip": -1,
    "**/*.rlc": -1,
    "**/*.rmf": -1,
    "**/*.rmvb": -1,
    "**/*.rpm": -1,
    "**/*.rtf": -1,
    "**/*.rz": -1,
    "**/*.s3m": -1,
    "**/*.s7z": -1,
    "**/*.scpt": -1,
    "**/*.sgi": -1,
    "**/*.shar": -1,
    "**/*.snap": -1,
    "**/*.sil": -1,
    "**/*.sketch": -1,
    "**/*.slk": -1,
    "**/*.smv": -1,
    "**/*.snk": -1,
    "**/*.so": -1,
    "**/*.stl": -1,
    "**/*.suo": -1,
    "**/*.sub": -1,
    "**/*.swf": -1,
    "**/*.tar": -1,
    "**/*.tbz": -1,
    "**/*.tbz2": -1,
    "**/*.tga": -1,
    "**/*.tgz": -1,
    "**/*.thmx": -1,
    "**/*.tif": -1,
    "**/*.tiff": -1,
    "**/*.tlz": -1,
    "**/*.ttc": -1,
    "**/*.ttf": -1,
    "**/*.txz": -1,
    "**/*.udf": -1,
    "**/*.uvh": -1,
    "**/*.uvi": -1,
    "**/*.uvm": -1,
    "**/*.uvp": -1,
    "**/*.uvs": -1,
    "**/*.uvu": -1,
    "**/*.viv": -1,
    "**/*.vob": -1,
    "**/*.war": -1,
    "**/*.wav": -1,
    "**/*.wax": -1,
    "**/*.wbmp": -1,
    "**/*.wdp": -1,
    "**/*.weba": -1,
    "**/*.webm": -1,
    "**/*.webp": -1,
    "**/*.whl": -1,
    "**/*.wim": -1,
    "**/*.wm": -1,
    "**/*.wma": -1,
    "**/*.wmv": -1,
    "**/*.wmx": -1,
    "**/*.woff": -1,
    "**/*.woff2": -1,
    "**/*.wrm": -1,
    "**/*.wvx": -1,
    "**/*.xbm": -1,
    "**/*.xif": -1,
    "**/*.xla": -1,
    "**/*.xlam": -1,
    "**/*.xls": -1,
    "**/*.xlsb": -1,
    "**/*.xlsm": -1,
    "**/*.xlsx": -1,
    "**/*.xlt": -1,
    "**/*.xltm": -1,
    "**/*.xltx": -1,
    "**/*.xm": -1,
    "**/*.xmind": -1,
    "**/*.xpi": -1,
    "**/*.xpm": -1,
    "**/*.xwd": -1,
    "**/*.xz": -1,
    "**/*.z": -1,
    "**/*.zip": -1,
    "**/*.zipx": -1,
    "**/*.MP4": -1,
    "**/*.JPG": -1,
    "**/*.json": 5242880,
    "**/*.yaml": 10485760,
    "**/*": 1048576
  }
}